LICENSE
MANIFEST.in
README.md
VERSION.txt
requirements.txt
setup.cfg
setup.py
ckanext/__init__.py
ckanext/datapackage_pipelines/__init__.py
ckanext/datapackage_pipelines/auth.py
ckanext/datapackage_pipelines/constants.py
ckanext/datapackage_pipelines/interfaces.py
ckanext/datapackage_pipelines/plugin.py
ckanext/datapackage_pipelines/utils.py
ckanext/datapackage_pipelines/views.py
ckanext/datapackage_pipelines/templates/datapackage_pipelines/dashboard.html
ckanext/datapackage_pipelines/tests/__init__.py
ckanext/datapackage_pipelines/tests/test_plugin.py
ckanext_datapackage_pipelines.egg-info/PKG-INFO
ckanext_datapackage_pipelines.egg-info/SOURCES.txt
ckanext_datapackage_pipelines.egg-info/dependency_links.txt
ckanext_datapackage_pipelines.egg-info/entry_points.txt
ckanext_datapackage_pipelines.egg-info/namespace_packages.txt
ckanext_datapackage_pipelines.egg-info/top_level.txt