Metadata-Version: 1.1
Name: ckanext-datapackage-pipelines
Version: 0.0.4
Summary: Integrate datapackage-pipelines with CKAN
Home-page: https://github.com/OriHoch/ckanext-datapackage_pipelines
Author: Ori Hoch
Author-email: ori@uumpa.com
License: AGPL
Keywords: CKAN datapackage-pipelines
Platform: UNKNOWN
Classifier: Development Status :: 4 - Beta
Classifier: License :: OSI Approved :: GNU Affero General Public License v3 or later (AGPLv3+)
Classifier: Programming Language :: Python :: 2.7
